aly/__init__.py
aly/__main__.py
aly/backends.py
aly/commands.py
aly/configuration.py
aly/fw_gcc.py
aly/log.py
aly/sim_questa.py
aly/sim_verilator.py
aly/sim_xsim.py
aly/synth_vivado.py
aly/synth_yosys.py
aly/util.py
aly/app/__init__.py
aly/app/basic.py
aly/app/config.py
aly/app/constraints.py
aly/app/firmware.py
aly/app/init.py
aly/app/ip.py
aly/app/lint.py
aly/app/main.py
aly/app/program.py
aly/app/rtl.py
aly/app/simulate.py
aly/app/synthesize.py
aly/app/terminal.py
aly/config/__init__.py
aly/config/project_config.py
aly/config/models/__init__.py
aly/config/models/core.py
aly/config/models/firmware.py
aly/config/models/helpers.py
aly/config/models/ip.py
aly/config/models/rtl.py
aly/config/models/testbench.py
aly/config/models/tools.py
aly/templates/__init__.py
aly/templates/loader.py
aly/templates/base/template.yaml
aly/templates/base/files/aly_commands.yml
aly/templates/base/files/aly_config.yaml.j2
aly/templates/base/files/gitignore
aly/templates/base/files/docs/README.md.j2
aly/templates/base/files/docs/api.rst.j2
aly/templates/base/files/docs/architecture.rst.j2
aly/templates/base/files/docs/development.rst.j2
aly/templates/base/files/docs/getting_started.rst.j2
aly/templates/base/files/docs/requirements.txt
aly/templates/base/files/docs/source/index.rst.j2
aly/templates/rv64i/template.yaml
aly/templates/rv64i/files/gitignore
aly/templates/rv64i/files/aly/config.yaml.j2
aly/templates/rv64i/files/aly/constraints.yaml
aly/templates/rv64i/files/aly/fpga.yaml
aly/templates/rv64i/files/aly/lint.yaml
aly/templates/rv64i/files/aly/sim.yaml.j2
aly/templates/rv64i/files/aly/synth.yaml.j2
aly/templates/rv64i/files/aly/toolchains.yaml
aly/templates/rv64i/files/docs/README.md.j2
aly/templates/rv64i/files/docs/requirements.txt
aly/templates/rv64i/files/docs/source/api.rst.j2
aly/templates/rv64i/files/docs/source/architecture.rst.j2
aly/templates/rv64i/files/docs/source/development.rst.j2
aly/templates/rv64i/files/docs/source/getting_started.rst.j2
aly_tool-0.1.2.dist-info/licenses/LICENSE
aly_tool-0.1.2.dist-info/METADATA
aly_tool-0.1.2.dist-info/WHEEL
aly_tool-0.1.2.dist-info/entry_points.txt
aly_tool-0.1.2.dist-info/top_level.txt
aly_tool-0.1.2.dist-info/RECORD
