Metadata-Version: 2.4
Name: aly-tool
Version: 0.1.2
Summary: ALY (Advanced Logic Yieldflow) is a Python-based RTL meta-tool that automates build, simulation, synthesis, and verification workflows across multiple EDA tools, providing a unified and efficient design flow for hardware projects. 
Author-email: Mohamed Aly <mohamedmenazaa@outlook.com>
Maintainer-email: Mohamed Aly <mohamedmenazaa@outlook.com>
Project-URL: Homepage, https://github.com/RWU-SOC/aly-tool
Project-URL: Documentation, https://rwu-soc.github.io/aly-tool
Project-URL: Repository, https://github.com/RWU-SOC/aly-tool
Project-URL: Issues, https://github.com/RWU-SOC/aly-tool/issues
Keywords: risc-v,soc,rtl,firmware,build-tool
Classifier: Development Status :: 4 - Beta
Classifier: Intended Audience :: Developers
Classifier: Topic :: Software Development :: Build Tools
Classifier: Topic :: Software Development :: Embedded Systems
Classifier: License :: OSI Approved :: Apache Software License
Classifier: Programming Language :: Python :: 3
Classifier: Programming Language :: Python :: 3.8
Classifier: Programming Language :: Python :: 3.9
Classifier: Programming Language :: Python :: 3.10
Classifier: Programming Language :: Python :: 3.11
Classifier: Programming Language :: Python :: 3.12
Classifier: Programming Language :: Python :: 3.13
Requires-Python: >=3.8
License-File: LICENSE
Requires-Dist: pyyaml>=5.1
Requires-Dist: jinja2>=3.0
Provides-Extra: terminal
Requires-Dist: pyserial>=3.5; extra == "terminal"
Provides-Extra: dev
Requires-Dist: pytest>=7.0; extra == "dev"
Requires-Dist: pytest-cov>=4.0; extra == "dev"
Requires-Dist: pytest-timeout>=2.1; extra == "dev"
Requires-Dist: sphinx>=4.0; extra == "dev"
Requires-Dist: sphinx-rtd-theme>=1.0; extra == "dev"
Requires-Dist: sphinx-copybutton>=0.5.0; extra == "dev"
Requires-Dist: sphinx-autobuild>=2021.3.14; extra == "dev"
Requires-Dist: myst-parser>=0.18; extra == "dev"
Requires-Dist: pyserial>=3.5; extra == "dev"
Provides-Extra: all
Requires-Dist: pyserial>=3.5; extra == "all"
Dynamic: license-file
